msglm/__init__.py
msglm/_modidx.py
msglm/core.py
msglm-0.0.12.dist-info/licenses/LICENSE
msglm-0.0.12.dist-info/METADATA
msglm-0.0.12.dist-info/WHEEL
msglm-0.0.12.dist-info/entry_points.txt
msglm-0.0.12.dist-info/top_level.txt
msglm-0.0.12.dist-info/RECORD
